README.md
setup.cfg
setup.py
Local_Variable_Manager.egg-info/PKG-INFO
Local_Variable_Manager.egg-info/SOURCES.txt
Local_Variable_Manager.egg-info/dependency_links.txt
Local_Variable_Manager.egg-info/entry_points.txt
Local_Variable_Manager.egg-info/requires.txt
Local_Variable_Manager.egg-info/top_level.txt
lvmanager/__init__.py
lvmanager/main.py
lvmanager/manager.py